lumbni_client/__init__.py
lumbni_client/api.py
lumbni_client/client.py
lumbni_client/exceptions.py
lumbni_client/response.py
tests/__init__.py
tests/test_client.py
tests/test_response.py
lumbni_client-1.0.1.dist-info/METADATA
lumbni_client-1.0.1.dist-info/WHEEL
lumbni_client-1.0.1.dist-info/top_level.txt
lumbni_client-1.0.1.dist-info/RECORD
