Metadata-Version: 2.2
Name: lumbni-client
Version: 1.0.1
Summary: A Python SDK for interacting with the Lumbni API
Author: Lumbni
Author-email: lumbniai@gamil.com
Classifier: Programming Language :: Python :: 3
Classifier: Operating System :: OS Independent
Requires-Python: >=3.6
Requires-Dist: requests>=2.28.1
Dynamic: author
Dynamic: author-email
Dynamic: classifier
Dynamic: description
Dynamic: description-content-type
Dynamic: requires-dist
Dynamic: requires-python
Dynamic: summary
